ulfom/__init__.py
ulfom/async_client.py
ulfom/client.py
ulfom/helpers.py
ulfom-0.1.4.dist-info/LICENSE
ulfom-0.1.4.dist-info/METADATA
ulfom-0.1.4.dist-info/WHEEL
ulfom-0.1.4.dist-info/RECORD
