Metadata-Version: 2.3
Name: ulfom
Version: 0.1.4
Summary: Python client library for the Ulfom API
License: MIT
Keywords: ulfom,api,client
Author: Dipankar Sarkar
Author-email: me@dipankar.name
Requires-Python: >=3.8,<4.0
Classifier: Development Status :: 4 - Beta
Classifier: Intended Audience :: Developers
Classifier: License :: OSI Approved :: MIT License
Classifier: Programming Language :: Python :: 3
Classifier: Programming Language :: Python :: 3.8
Classifier: Programming Language :: Python :: 3.9
Classifier: Programming Language :: Python :: 3.10
Classifier: Programming Language :: Python :: 3.11
Classifier: Programming Language :: Python :: 3.12
Classifier: Programming Language :: Python :: 3.13
Requires-Dist: aiohttp (>=3.9.1,<4.0.0)
Requires-Dist: requests (>=2.31.0,<3.0.0)
Project-URL: Documentation, https://github.com/ulfom/ulfom-python#readme
Project-URL: Repository, https://github.com/ulfom/ulfom-python
